addon_utils/__init__.pyi
addon_utils/py.typed
animsys_refactor/__init__.pyi
animsys_refactor/py.typed
aud/__init__.pyi
aud/py.typed
bge/__init__.pyi
bge/py.typed
bge/app/__init__.pyi
bge/constraints/__init__.pyi
bge/types/__init__.pyi
bge/types/BL_ActionActuator/__init__.pyi
bge/types/BL_ArmatureActuator/__init__.pyi
bge/types/BL_ArmatureBone/__init__.pyi
bge/types/BL_ArmatureChannel/__init__.pyi
bge/types/BL_ArmatureConstraint/__init__.pyi
bge/types/BL_ArmatureObject/__init__.pyi
bge/types/BL_Shader/__init__.pyi
bge/types/BL_Texture/__init__.pyi
bge/types/EXP_ListValue/__init__.pyi
bge/types/EXP_PropValue/__init__.pyi
bge/types/EXP_PyObjectPlus/__init__.pyi
bge/types/EXP_Value/__init__.pyi
bge/types/KX_2DFilter/__init__.pyi
bge/types/KX_2DFilterManager/__init__.pyi
bge/types/KX_2DFilterOffScreen/__init__.pyi
bge/types/KX_ArmatureSensor/__init__.pyi
bge/types/KX_BatchGroup/__init__.pyi
bge/types/KX_BlenderMaterial/__init__.pyi
bge/types/KX_BoundingBox/__init__.pyi
bge/types/KX_Camera/__init__.pyi
bge/types/KX_CameraActuator/__init__.pyi
bge/types/KX_CharacterWrapper/__init__.pyi
bge/types/KX_CollisionContactPoint/__init__.pyi
bge/types/KX_CollisionSensor/__init__.pyi
bge/types/KX_ConstraintActuator/__init__.pyi
bge/types/KX_ConstraintWrapper/__init__.pyi
bge/types/KX_CubeMap/__init__.pyi
bge/types/KX_FontObject/__init__.pyi
bge/types/KX_GameActuator/__init__.pyi
bge/types/KX_GameObject/__init__.pyi
bge/types/KX_LibLoadStatus/__init__.pyi
bge/types/KX_LightObject/__init__.pyi
bge/types/KX_LodLevel/__init__.pyi
bge/types/KX_LodManager/__init__.pyi
bge/types/KX_Mesh/__init__.pyi
bge/types/KX_MouseActuator/__init__.pyi
bge/types/KX_MouseFocusSensor/__init__.pyi
bge/types/KX_NavMeshObject/__init__.pyi
bge/types/KX_NearSensor/__init__.pyi
bge/types/KX_NetworkMessageActuator/__init__.pyi
bge/types/KX_NetworkMessageSensor/__init__.pyi
bge/types/KX_ObjectActuator/__init__.pyi
bge/types/KX_ParentActuator/__init__.pyi
bge/types/KX_PlanarMap/__init__.pyi
fake_bge_module_0.2.5-20241013.dist-info/METADATA
fake_bge_module_0.2.5-20241013.dist-info/WHEEL
fake_bge_module_0.2.5-20241013.dist-info/top_level.txt
fake_bge_module_0.2.5-20241013.dist-info/RECORD
